amd2pdf/__init__.py
amd2pdf/__main__.py
amd2pdf/cli.py
amd2pdf/core.py
amd2pdf/helpers.py
amd2pdf/md2pdf.js
amd2pdf/tasks.py
amd2pdf/rsrc/style.css
amd2pdf-0.1.3.dist-info/LICENSE.md
amd2pdf-0.1.3.dist-info/METADATA
amd2pdf-0.1.3.dist-info/WHEEL
amd2pdf-0.1.3.dist-info/entry_points.txt
amd2pdf-0.1.3.dist-info/top_level.txt
amd2pdf-0.1.3.dist-info/RECORD
