Metadata-Version: 2.1
Name: amd2pdf
Version: 0.1.3
Summary: Another markdown to pdf with TOC and page index support
Home-page: https://github.com/tenuki/amd2pdf
Author: david weil
Author-email: david.weil@endlesstruction.com.ar
License: GNU General Public License v3.0
Platform: UNKNOWN
Requires-Python: >=3
Requires-Dist: doit
Requires-Dist: jinja2
